xbt/__init__.py
xbt/build.py
xbt/cli.py
xbt/connections.py
xbt/graph.py
xbt/macros.py
xbt/models.py
xbt-0.3.1.dist-info/LICENSE
xbt-0.3.1.dist-info/METADATA
xbt-0.3.1.dist-info/WHEEL
xbt-0.3.1.dist-info/entry_points.txt
xbt-0.3.1.dist-info/top_level.txt
xbt-0.3.1.dist-info/RECORD
